docs/conf.py
docs/contributing.rst
docs/index.rst
docs/installation.rst
infra/.dockerignore
infra/.gcloudignore
infra/Dockerfile
infra/Justfile
infra/cors.json
semantic_navigator/__init__.py
semantic_navigator/constants.py
semantic_navigator/py.typed
semantic_navigator/query_embedding.py
semantic_navigator/train.py
semantic_navigator/app/__init__.py
semantic_navigator/app/views.py
semantic_navigator/app/static/loader.css
semantic_navigator/app/static/protocol-components.min.css
semantic_navigator/app/static/protocol-components.min.css.map
semantic_navigator/app/static/protocol.min.css
semantic_navigator/app/static/protocol.min.css.map
semantic_navigator/app/templates/base.html
semantic_navigator/app/templates/index.html
semantic_navigator/app/templates/results.html
semantic_navigator/app/templates/train.html
semantic_navigator/bin/__init__.py
semantic_navigator/bin/fetch_model_for_sem_nav.py
semantic_navigator/bin/semantic_navigator.py
semantic_navigator/data/__init__.py
semantic_navigator/tests/conftest.py
semantic_navigator/tests/test_empty.py
semantic_navigator-0.2.0.dist-info/LICENSE
semantic_navigator-0.2.0.dist-info/METADATA
semantic_navigator-0.2.0.dist-info/WHEEL
semantic_navigator-0.2.0.dist-info/entry_points.txt
semantic_navigator-0.2.0.dist-info/top_level.txt
semantic_navigator-0.2.0.dist-info/RECORD
