Metadata-Version: 2.1
Name: semantic-navigator
Version: 0.2.0
Summary: An active learning approach to query and search through large archival datasets.
Author-email: Eva Maxfield Brown <evamxb@uw.edu>, Madeleine Grunde-McLaughlin <mgrunde@uw.edu>, Isabella Pestovski <pestoi@uw.edu>, Lanyi Zhu <lanyizhu@uw.edu>
License: MPLv2.0
Project-URL: Homepage, https://github.com/CouncilDataProject/semantic-navigator
Project-URL: Bug Tracker, https://github.com/CouncilDataProject/semantic-navigator/issues
Project-URL: Documentation, https://CouncilDataProject.github.io/semantic-navigator
Project-URL: User Support, https://github.com/CouncilDataProject/semantic-navigator/issues
Classifier: Development Status :: 4 - Beta
Classifier: Natural Language :: English
Classifier: License :: OSI Approved :: Mozilla Public License 2.0 (MPL 2.0)
Classifier: Programming Language :: Python :: 3.8
Classifier: Programming Language :: Python :: 3.9
Classifier: Programming Language :: Python :: 3.10
Classifier: Programming Language :: Python :: 3.11
Requires-Python: >=3.8
License-File: LICENSE
Requires-Dist: cdp-data (==0.0.10)
Requires-Dist: flask (~=2.2.3)
Requires-Dist: gcsfs
Requires-Dist: pyarrow (~=12.0.0)
Requires-Dist: sentence-transformers (~=2.2.2)
Provides-Extra: dev
Requires-Dist: ipython (>=8.4.0) ; extra == 'dev'
Requires-Dist: jupyterlab ; extra == 'dev'
Requires-Dist: umap-learn[plot] (~=0.5.3) ; extra == 'dev'
Provides-Extra: docs
Requires-Dist: m2r2 (>=0.2.7) ; extra == 'docs'
Requires-Dist: Sphinx (>=4.0.0) ; extra == 'docs'
Requires-Dist: furo (>=2022.4.7) ; extra == 'docs'
Requires-Dist: numpydoc ; extra == 'docs'
Requires-Dist: sphinx-copybutton ; extra == 'docs'
Requires-Dist: docutils (<0.19,>=0.18) ; extra == 'docs'
Provides-Extra: lint
Requires-Dist: black (>=22.3.0) ; extra == 'lint'
Requires-Dist: check-manifest (>=0.48) ; extra == 'lint'
Requires-Dist: ruff (>=0.0.216) ; extra == 'lint'
Requires-Dist: mypy (>=0.790) ; extra == 'lint'
Requires-Dist: pre-commit (>=2.20.0) ; extra == 'lint'
Provides-Extra: test
Requires-Dist: coverage (>=5.1) ; extra == 'test'
Requires-Dist: pytest (>=5.4.3) ; extra == 'test'
Requires-Dist: pytest-cov (>=2.9.0) ; extra == 'test'
Requires-Dist: pytest-raises (>=0.11) ; extra == 'test'
